authutils/__init__.py
authutils/dbgap.py
authutils/errors.py
authutils/globals.py
authutils/oauth2/__init__.py
authutils/oauth2/client/__init__.py
authutils/oauth2/client/authorize.py
authutils/oauth2/client/blueprint.py
authutils/oauth2/client/client.py
authutils/testing/__init__.py
authutils/testing/fixtures/__init__.py
authutils/testing/fixtures/keys.py
authutils/token/__init__.py
authutils/token/core.py
authutils/token/fastapi.py
authutils/token/keys.py
authutils/token/validate.py
authutils/user.py
authutils-7.2.1.dist-info/METADATA
authutils-7.2.1.dist-info/WHEEL
authutils-7.2.1.dist-info/licenses/LICENSE
authutils-7.2.1.dist-info/licenses/NOTICE
authutils-7.2.1.dist-info/RECORD
