Metadata-Version: 2.4
Name: authutils
Version: 7.2.1
Summary: Gen3 auth utility functions
License: Apache-2.0
License-File: LICENSE
License-File: NOTICE
Author: CTDS UChicago
Author-email: cdis@uchicago.edu
Requires-Python: >=3.13,<4.0
Classifier: License :: OSI Approved :: Apache Software License
Classifier: Programming Language :: Python :: 3
Classifier: Programming Language :: Python :: 3.13
Classifier: Programming Language :: Python :: 3.14
Provides-Extra: datamodelutils
Provides-Extra: fastapi
Provides-Extra: flask
Requires-Dist: Flask (<=2.3.3) ; extra == "flask"
Requires-Dist: authlib (>=1.6.5)
Requires-Dist: cached-property (>=1.4,<2.0)
Requires-Dist: cdiserrors
Requires-Dist: cdislogging
Requires-Dist: cryptography (>=44.0.1,<45.0.0)
Requires-Dist: datamodelutils ; extra == "datamodelutils"
Requires-Dist: fastapi (>=0.65.2,<0.66.0) ; extra == "fastapi"
Requires-Dist: httpx (>=0.23.0,<1.0.0)
Requires-Dist: pyjwt[crypto] (>=2.4.0,<3.0)
Requires-Dist: starlette
Requires-Dist: werkzeug
Requires-Dist: xmltodict (>=0.9,<1.0)
